luabins/__init__.py
luabins/byte_utils.py
luabins/constants.py
luabins/lua_table_key.py
luabins/luabins.py
luabins_py-1.1.0.dist-info/LICENSE
luabins_py-1.1.0.dist-info/METADATA
luabins_py-1.1.0.dist-info/WHEEL
luabins_py-1.1.0.dist-info/top_level.txt
luabins_py-1.1.0.dist-info/RECORD
