Metadata-Version: 2.1
Name: luabins-py
Version: 1.1.0
Summary: A library to encode/decode luabins serialized data in python
Home-page: https://github.com/zsennenga/luabins_py
Author: Zach Ennenga
Author-email: astrozees@gmail.com
License: MIT License
Platform: UNKNOWN
